coreutility/__init__.py
coreutility/date_utility.py
coreutility/file_utility.py
coreutility/collection/__init__.py
coreutility/collection/dictionary_utility.py
coreutility/date/NanoTimestamp.py
coreutility/date/__init__.py
coreutility/json/__init__.py
coreutility/json/json_utility.py
coreutility/number/BigFloatAdd.py
coreutility/number/BigFloatOperation.py
coreutility/number/BigFloatSubtract.py
coreutility/number/__init__.py
coreutility/string/__init__.py
coreutility/string/string_utility.py
persuader_technology_automata_utilities-0.2.3.dist-info/LICENSE
persuader_technology_automata_utilities-0.2.3.dist-info/METADATA
persuader_technology_automata_utilities-0.2.3.dist-info/WHEEL
persuader_technology_automata_utilities-0.2.3.dist-info/top_level.txt
persuader_technology_automata_utilities-0.2.3.dist-info/RECORD
