Metadata-Version: 2.1
Name: persuader-technology-automata-utilities
Version: 0.2.3
Summary: Automata Utilities
Author: Persuader Technology
Author-email: software@persuader.technology
License: UNLICENSE
Classifier: Programming Language :: Python :: 3
License-File: LICENSE
Requires-Dist: persuader-technology-automata-core (>=0.6.0)
